PyOOPy/PyOOPy.py
PyOOPy/__init__.py
PyOOPy-0.1.1.dist-info/LICENSE.txt
PyOOPy-0.1.1.dist-info/METADATA
PyOOPy-0.1.1.dist-info/WHEEL
PyOOPy-0.1.1.dist-info/top_level.txt
PyOOPy-0.1.1.dist-info/RECORD
